tim_the_enchanter/__init__.py
tim_the_enchanter/tim_the_enchanter.py
tim_the_enchanter-1.0.0.dist-info/licenses/LICENSE
tim_the_enchanter-1.0.0.dist-info/METADATA
tim_the_enchanter-1.0.0.dist-info/WHEEL
tim_the_enchanter-1.0.0.dist-info/top_level.txt
tim_the_enchanter-1.0.0.dist-info/RECORD
