Metadata-Version: 2.4
Name: tim-the-enchanter
Version: 1.0.0
Summary: A lightweight, flexible performance tracking library for Python applications
Author-email: Jeff Fohl <jeff@fohl.com>
Project-URL: Homepage, https://github.com/jefffohl/tim-the-enchanter
Project-URL: Bug Tracker, https://github.com/jefffohl/tim-the-enchanter/issues
Classifier: Programming Language :: Python :: 3
Classifier: License :: OSI Approved :: MIT License
Classifier: Operating System :: OS Independent
Classifier: Intended Audience :: Developers
Classifier: Topic :: Software Development :: Libraries :: Python Modules
Classifier: Topic :: Software Development :: Testing
Classifier: Topic :: System :: Monitoring
Requires-Python: >=3.7
License-File: LICENSE
Dynamic: license-file
